{
  "_class": "symbolInstance",
  "booleanOperation": -1,
  "do_objectID": "E63B4DFC-BB69-4FD5-9C4D-70C350F5D5DE",
  "exportOptions": {
    "_class": "exportOptions",
    "exportFormats": [
    ],
    "includedLayerIds": [
    ],
    "layerOptions": 0,
    "shouldTrim": false
  },
  "frame": {
    "_class": "rect",
    "constrainProportions": false,
    "height": 76,
    "width": 326,
    "x": 27,
    "y": 202
  },
  "horizontalSpacing": 0,
  "isFixedToViewport": false,
  "isFlippedHorizontal": false,
  "isFlippedVertical": false,
  "isLocked": false,
  "isVisible": true,
  "layerListExpandedType": 0,
  "name": "sumbols",
  "nameIsFixed": false,
  "overrideValues": [
    {
      "_class": "overrideValue",
      "do_objectID": "9A4059D4-EFF2-4ED5-80D5-8FABAD345382",
      "overrideName": "FF949114-45A7-49D1-9082-A3AF73C32B95/8A73DC63-FFAA-469E-BCD6-2A6CD4455005_stringValue",
      "value": "Name "
    },
    {
      "_class": "overrideValue",
      "do_objectID": "6DFCF812-48D1-4687-901E-D7FEEF052E28",
      "overrideName": "12C1A830-2056-4B78-92C1-3D2324FB235C_stringValue",
      "value": "Enter your name"
    }
  ],
  "resizingConstraint": 63,
  "resizingType": 0,
  "rotation": 0,
  "scale": 1,
  "shouldBreakMaskChain": false,
  "style": {
    "_class": "style",
    "endMarkerType": 0,
    "miterLimit": 10,
    "startMarkerType": 0,
    "windingRule": 1
  },
  "symbolID": "B3F7BF5F-00CD-4DAC-982B-5C49D653E6FB",
  "verticalSpacing": 0
}